xml_image_converter/__init__.py
xml_image_converter/bundle.mjs
xml_image_converter/element.py
xml_image_converter/package.json
xml_image_converter/template.py
xml_image_converter-0.0.14.dist-info/LICENSE
xml_image_converter-0.0.14.dist-info/METADATA
xml_image_converter-0.0.14.dist-info/WHEEL
xml_image_converter-0.0.14.dist-info/entry_points.txt
xml_image_converter-0.0.14.dist-info/top_level.txt
xml_image_converter-0.0.14.dist-info/RECORD
