Metadata-Version: 2.1
Name: xml_image_converter
Version: 0.0.14
Summary: python-node.js package sample lib
Home-page: https://github.com/miridih/xml-image-converter
Author: jhmun
Author-email: jhmun@miridih.com
Classifier: Programming Language :: Python :: 3
Classifier: License :: OSI Approved :: MIT License
Classifier: Operating System :: OS Independent
Requires-Python: >=3.6
License-File: LICENSE
